LICENSE
simple_ascii_tables/__init__.py
simple_ascii_tables/ascii_table.py
simple_ascii_tables/build.py
simple_ascii_tables/terminal_io.py
simple_ascii_tables/width_and_alignment.py
simple_ascii_tables-1.0.0.dist-info/LICENSE
simple_ascii_tables-1.0.0.dist-info/METADATA
simple_ascii_tables-1.0.0.dist-info/WHEEL
simple_ascii_tables-1.0.0.dist-info/RECORD
