Metadata-Version: 2.1
Name: simple-ascii-tables
Version: 1.0.0
Summary: Simple, minimal, dependency-free ASCII tables for Python.
Home-page: https://www.kerykeion.net/
License: MIT
Keywords: ascii,table,ascii-table,ascii-tables,simple,simple-ascii-table
Author: Giacomo Battaglia
Author-email: kerykeion.astrology@gmail.com
Requires-Python: >=3.9,<4.0
Classifier: Development Status :: 5 - Production/Stable
Classifier: Intended Audience :: Developers
Classifier: Intended Audience :: Information Technology
Classifier: License :: OSI Approved :: GNU General Public License (GPL)
Classifier: License :: OSI Approved :: MIT License
Classifier: Operating System :: OS Independent
Classifier: Programming Language :: Python :: 3
Classifier: Programming Language :: Python :: 3.9
Classifier: Programming Language :: Python :: 3.10
Classifier: Programming Language :: Python :: 3.11
Classifier: Programming Language :: Python :: 3.12
Classifier: Programming Language :: Python :: 3 :: Only
Classifier: Topic :: Software Development :: Libraries
Classifier: Topic :: Software Development :: Libraries :: Application Frameworks
Classifier: Topic :: Software Development :: Libraries :: Python Modules
Classifier: Typing :: Typed
Project-URL: Repository, https://www.kerykeion.net/
